yx_weather/__init__.py
yx_weather/weather.py
yx_weather-0.1.0.dist-info/METADATA
yx_weather-0.1.0.dist-info/WHEEL
yx_weather-0.1.0.dist-info/entry_points.txt
yx_weather-0.1.0.dist-info/RECORD
