Metadata-Version: 2.4
Name: yx-weather
Version: 0.1.0
Summary: Add your description here
Author-email: 御雪 <wb-spf530106@alibaba-inc.com>
Requires-Python: >=3.10
Requires-Dist: httpx>=0.28.1
Requires-Dist: mcp>=1.6.0
